calculator_sf/__init__.py
calculator_sf/calculator.py
calculator_sf-0.5.0.dist-info/LICENSE
calculator_sf-0.5.0.dist-info/WHEEL
calculator_sf-0.5.0.dist-info/METADATA
calculator_sf-0.5.0.dist-info/RECORD
