Metadata-Version: 2.1
Name: calculator_sf
Version: 0.5.0
Summary: a simple calculator
Author-email: Shanti Flagg <shanti.flagg@gmail.com>
Classifier: License :: OSI Approved :: MIT License
Project-URL: Home, https://github.com/TuringCollegeSubmissions/sflagg-DWWP.1.5
